README.rst
setup.py
cloudhealth/__init__.py
cloudhealth/accounts.py
cloudhealth/assets.py
cloudhealth/cli.py
cloudhealth/client.py
cloudhealth/cost.py
cloudhealth/exceptions.py
cloudhealth/reports.py
cloudhealth/usage.py
cloudhealth.egg-info/PKG-INFO
cloudhealth.egg-info/SOURCES.txt
cloudhealth.egg-info/dependency_links.txt
cloudhealth.egg-info/entry_points.txt
cloudhealth.egg-info/requires.txt
cloudhealth.egg-info/top_level.txt