Metadata-Version: 1.0
Name: cloudhealth
Version: 0.1.1
Summary: A REST Client for Cloudhealth
Home-page: UNKNOWN
Author: Nir Cohen
Author-email: nir36g@gmail.com
License: LICENSE
Platform: UNKNOWN
